sszz/__init__.py
sszz/sszz.py
sszz-0.0.5.dist-info/LICENSE
sszz-0.0.5.dist-info/METADATA
sszz-0.0.5.dist-info/WHEEL
sszz-0.0.5.dist-info/entry_points.txt
sszz-0.0.5.dist-info/top_level.txt
sszz-0.0.5.dist-info/RECORD
