Metadata-Version: 2.1
Name: sszz
Version: 0.0.5
Summary: Tool to retrieve the a future commit that has refactored a given commit (simple SZZ).
Home-page: https://github.com/luiscruz/sszz
Author: Luis Cruz
Author-email: luismirandacruz@gmail.com
License: UNKNOWN
Platform: UNKNOWN
Classifier: Programming Language :: Python :: 3
Classifier: License :: OSI Approved :: Apache Software License
Classifier: Operating System :: OS Independent
Requires-Dist: Click (==7.0)
Requires-Dist: GitPython (==2.1.11)
